xcosmo/__init__.py
xcosmo/cosmograph.py
xcosmo/ingress_framework.py
xcosmo/ingress_functions.py
xcosmo-0.0.2.dist-info/METADATA
xcosmo-0.0.2.dist-info/WHEEL
xcosmo-0.0.2.dist-info/licenses/LICENSE
xcosmo-0.0.2.dist-info/RECORD
