Metadata-Version: 2.4
Name: xcosmo
Version: 0.0.2
Summary: Python extensions of cosmograph
Project-URL: Homepage, https://github.com/cosmograph-org/xcosmo
Project-URL: Repository, https://github.com/cosmograph-org/xcosmo
Project-URL: Documentation, https://cosmograph-org.github.io/xcosmo
License: mit
License-File: LICENSE
Requires-Python: >=3.10
Provides-Extra: dev
Requires-Dist: pytest-cov>=4.0; extra == 'dev'
Requires-Dist: pytest>=7.0; extra == 'dev'
Requires-Dist: ruff>=0.1.0; extra == 'dev'
Provides-Extra: docs
Requires-Dist: sphinx-rtd-theme>=1.0; extra == 'docs'
Requires-Dist: sphinx>=6.0; extra == 'docs'
